atticmatic/command.py
atticmatic/verbosity.py
atticmatic/config.py
atticmatic/__init__.py
atticmatic/backends/borg.py
atticmatic/backends/shared.py
atticmatic/backends/attic.py
atticmatic/backends/__init__.py
atticmatic/tests/builtins.py
atticmatic/tests/__init__.py
atticmatic/tests/unit/test_config.py
atticmatic/tests/unit/__init__.py
atticmatic/tests/unit/test_command.py
atticmatic/tests/unit/backends/__init__.py
atticmatic/tests/unit/backends/test_shared.py
atticmatic/tests/integration/test_config.py
atticmatic/tests/integration/test_version.py
atticmatic/tests/integration/__init__.py
atticmatic/tests/integration/test_command.py
atticmatic-0.1.8.dist-info/pydist.json
atticmatic-0.1.8.dist-info/top_level.txt
atticmatic-0.1.8.dist-info/DESCRIPTION.rst
atticmatic-0.1.8.dist-info/WHEEL
atticmatic-0.1.8.dist-info/RECORD
atticmatic-0.1.8.dist-info/METADATA
atticmatic-0.1.8.dist-info/entry_points.txt
atticmatic-0.1.8.data/scripts/atticmatic
atticmatic-0.1.8.data/scripts/borgmatic
