Metadata-Version: 2.0
Name: atticmatic
Version: 0.1.8
Summary: A wrapper script for Attic/Borg backup software that creates and prunes backups
Home-page: https://torsion.org/atticmatic
Author: Dan Helfman
Author-email: witten@torsion.org
License: UNKNOWN
Download-URL: https://torsion.org/hg/atticmatic/archive/0.1.8.tar.gz
Platform: UNKNOWN
Classifier: Development Status :: 5 - Production/Stable
Classifier: Environment :: Console
Classifier: Intended Audience :: System Administrators
Classifier: License :: OSI Approved :: GNU General Public License v3 (GPLv3)
Classifier: Programming Language :: Python
Classifier: Topic :: Security :: Cryptography
Classifier: Topic :: System :: Archiving :: Backup
